pidata/__init__.py
pidata/meta.py
pidata/pull.py
pidata/utils.py
PIdata-0.3.1.dist-info/LICENSE
PIdata-0.3.1.dist-info/METADATA
PIdata-0.3.1.dist-info/WHEEL
PIdata-0.3.1.dist-info/top_level.txt
PIdata-0.3.1.dist-info/RECORD
