Metadata-Version: 2.1
Name: PIdata
Version: 0.3.1
Summary: An easy-to-use connector for the OSI PI historian
Author-email: Venanzio Petrarolo <petrarolov@gmail.com>
Project-URL: Homepage, https://github.com/Petrarolo/PIdata
Project-URL: Issues, https://github.com/Petrarolo/PIdata/issues
Keywords: OSI,PI,Connector,Historian,Process,Control,Automation,Engineering
Classifier: Development Status :: 3 - Alpha
Classifier: Programming Language :: Python :: 3
Classifier: License :: OSI Approved :: MIT License
Classifier: Operating System :: OS Independent
Requires-Python: >=3.7
License-File: LICENSE
Requires-Dist: pythonnet
Requires-Dist: numpy
Requires-Dist: pandas
